sqlite_colorbrewer/__init__.py
sqlite_colorbrewer/colorbrewer.py
sqlite_colorbrewer-0.2.dist-info/LICENSE
sqlite_colorbrewer-0.2.dist-info/METADATA
sqlite_colorbrewer-0.2.dist-info/WHEEL
sqlite_colorbrewer-0.2.dist-info/entry_points.txt
sqlite_colorbrewer-0.2.dist-info/top_level.txt
sqlite_colorbrewer-0.2.dist-info/RECORD
