Metadata-Version: 2.1
Name: sqlite-colorbrewer
Version: 0.2
Summary: A custom function to use ColorBrewer scales in SQLite queries
Home-page: https://github.com/eyeseast/sqlite-colorbrewer
Author: Chris Amico
License: Apache License, Version 2.0
Project-URL: Issues, https://github.com/eyeseast/sqlite-colorbrewer/issues
Project-URL: CI, https://github.com/eyeseast/sqlite-colorbrewer/actions
Project-URL: Changelog, https://github.com/eyeseast/sqlite-colorbrewer/releases
Platform: UNKNOWN
Classifier: Framework :: Datasette
Classifier: License :: OSI Approved :: Apache Software License
Requires-Python: >=3.6
License-File: LICENSE
Provides-Extra: test
Requires-Dist: datasette ; extra == 'test'
Requires-Dist: pytest ; extra == 'test'
Requires-Dist: pytest-asyncio ; extra == 'test'
